[
  {
    "path": "posts/welcome/",
    "title": "Welcome to Portfolio - Bruno Possamai",
    "description": "Welcome to our new blog, Portfolio - Bruno Possamai. We hope you enjoy \nreading what we have to say!",
    "author": [
      {
        "name": "Nora Jones",
        "url": "https://example.com/norajones"
      }
    ],
    "date": "2022-03-13",
    "categories": [],
    "contents": "\r\n\r\n\r\n\r\n",
    "preview": {},
    "last_modified": "2022-03-13T22:57:33-03:00",
    "input_file": {}
  },
  {
    "path": "posts/2022-03-13-anlise-de-dados-da-base-rais/",
    "title": "Análise da base RAIS",
    "description": "Essa análise tem como objetivo analisar os salários na base da RAIS. Esse projeto foi feito na semana Data Science na Prática da Curso-R.",
    "author": [
      {
        "name": "Bruno Anderson Possamai",
        "url": "https://example.com/norajones"
      }
    ],
    "date": "2022-03-13",
    "categories": [],
    "contents": "\r\nNesse relatório estamos interessados em responder a seguinte pergunta:\r\n“Quanto ganha um cientista de dados?”\r\nPara isso vamos utilizar a base da RAIS anonimizada.\r\nAcessando os dados da RAIS\r\nVamos utilizar o data lake da iniciativa Base dos Dados.\r\n\r\n\r\n\r\nAbaixo está o bloco de código que carrega as primeiras 5 linhas da tabela de microdados.\r\n\r\n# A tibble: 5 x 66\r\n    ano sigla_uf id_municipio tipo_vinculo vinculo_ativo_3112\r\n  <int> <chr>    <chr>        <chr>                     <int>\r\n1  1985 AC       1200054      1                             1\r\n2  1985 AC       1200054      1                             1\r\n3  1985 AC       1200054      1                             1\r\n4  1985 AC       1200054      1                             1\r\n5  1985 AC       1200054      1                             1\r\n# ... with 61 more variables: tipo_admissao <chr>,\r\n#   mes_admissao <int>, mes_desligamento <int>,\r\n#   motivo_desligamento <chr>, causa_desligamento_1 <chr>,\r\n#   causa_desligamento_2 <chr>, causa_desligamento_3 <chr>,\r\n#   faixa_tempo_emprego <chr>, tempo_emprego <dbl>,\r\n#   faixa_horas_contratadas <chr>,\r\n#   quantidade_horas_contratadas <int>, ...\r\n\r\n\r\n\r\n\r\n",
    "preview": {},
    "last_modified": "2022-03-22T19:08:59-03:00",
    "input_file": "anlise-de-dados-da-base-rais.knit.md"
  }
]
